deepctr/__init__.py
deepctr/inputs.py
deepctr/utils.py
deepctr/contrib/__init__.py
deepctr/contrib/rnn.py
deepctr/contrib/rnn_v2.py
deepctr/contrib/utils.py
deepctr/layers/__init__.py
deepctr/layers/activation.py
deepctr/layers/core.py
deepctr/layers/interaction.py
deepctr/layers/normalization.py
deepctr/layers/sequence.py
deepctr/layers/utils.py
deepctr/models/__init__.py
deepctr/models/afm.py
deepctr/models/autoint.py
deepctr/models/ccpm.py
deepctr/models/dcn.py
deepctr/models/deepfm.py
deepctr/models/dien.py
deepctr/models/din.py
deepctr/models/dsin.py
deepctr/models/fgcnn.py
deepctr/models/fibinet.py
deepctr/models/fnn.py
deepctr/models/mlr.py
deepctr/models/nfm.py
deepctr/models/onn.py
deepctr/models/pnn.py
deepctr/models/wdl.py
deepctr/models/xdeepfm.py
easymatch-0.0.0.dist-info/METADATA
easymatch-0.0.0.dist-info/RECORD
easymatch-0.0.0.dist-info/WHEEL
easymatch-0.0.0.dist-info/top_level.txt
