Metadata-Version: 2.1
Name: easymatch
Version: 0.0.0
Summary: EasyMatch
Home-page: https://github.com/shenweichen/easymatch
Author: Weichen Shen
Author-email: wcshen1994@163.com
License: Apache-2.0
Download-URL: https://github.com/shenweichen/easymatch/tags
Keywords: match,deep learning,tensorflow,tensor,keras
Platform: UNKNOWN
Classifier: License :: OSI Approved :: Apache Software License
Classifier: Operating System :: OS Independent
Classifier: Intended Audience :: Developers
Classifier: Intended Audience :: Education
Classifier: Intended Audience :: Science/Research
Classifier: Programming Language :: Python :: 3
Classifier: Programming Language :: Python :: 2.7
Classifier: Programming Language :: Python :: 3.5
Classifier: Programming Language :: Python :: 3.6
Classifier: Programming Language :: Python :: 3.7
Classifier: Topic :: Scientific/Engineering
Classifier: Topic :: Scientific/Engineering :: Artificial Intelligence
Classifier: Topic :: Software Development
Classifier: Topic :: Software Development :: Libraries
Classifier: Topic :: Software Development :: Libraries :: Python Modules
Requires-Python: >=2.7,!=3.0.*,!=3.1.*,!=3.2.*,!=3.3.*,!=3.4.*
Provides-Extra: cpu
Provides-Extra: gpu
Requires-Dist: h5py
Requires-Dist: requests
Provides-Extra: cpu
Requires-Dist: tensorflow (!=1.7.*,!=1.8.*,>=1.4.0); extra == 'cpu'
Provides-Extra: gpu
Requires-Dist: tensorflow-gpu (!=1.7.*,!=1.8.*,>=1.4.0); extra == 'gpu'
